{"total":96,"pageSize":12,"pageCount":8,"data":[{"title":"前端设计模式应用","uid":"4fde660230560945997cb0c9305b7a1e","slug":"青训营--前端设计模式应用","date":"2022-02-07T02:42:27.000Z","updated":"2025-07-14T15:12:20.472Z","comments":true,"path":"api/articles/青训营--前端设计模式应用.json","keywords":"web前端开发,web前端博客,个人博客,html,css,javascript,vue,react","cover":"https://img-blog.csdnimg.cn/3112c385d3c845d4b0305beebbc3ffdf.jpeg","text":"前端设计模式是在前端开发中常用的一种解决问题的方法论，它可以帮助开发者更好地组织和管理代码。本文将介绍前端设计模式的应用，包括常见的设计模式如单例模式、观察者模式、工厂模式等，并深入探讨它们的原理和适用场景。...","permalink":"/post/青训营--前端设计模式应用","photos":[],"count_time":{"symbolsCount":"9.4k","symbolsTime":"9 mins."},"categories":[{"name":"前端","slug":"前端","count":48,"path":"api/categories/前端.json"}],"tags":[{"name":"字节跳动青训营","slug":"字节跳动青训营","count":21,"path":"api/tags/字节跳动青训营.json"}],"author":{"name":"会思想的苇草i","slug":"blog-author","avatar":"/img/avatar.jpg","link":"/","description":"日拱一卒，功不唐捐 <br/> With each day's arduous effort,<br/>no achievement shall be in vain","socials":{"github":"https://github.com/Thinkingreedi","twitter":"","stackoverflow":"","wechat":"","qq":"","weibo":"","zhihu":"","csdn":"https://blog.csdn.net/ASHIYI66","juejin":"https://juejin.cn/user/4284166567110935","customs":{}}},"feature":false},{"title":"Typescript快速入门","uid":"fc3331da72f382869606f6a944c6cf7d","slug":"青训营--Typescript快速入门","date":"2022-02-05T10:40:59.000Z","updated":"2025-07-14T15:12:20.471Z","comments":true,"path":"api/articles/青训营--Typescript快速入门.json","keywords":"web前端开发,web前端博客,个人博客,html,css,javascript,vue,react","cover":"https://img-blog.csdnimg.cn/3112c385d3c845d4b0305beebbc3ffdf.jpeg","text":"TypeScript是一种由Microsoft开发的语言，它是JavaScript的一个超集，增加了静态类型和面向对象编程等特性。本文将引导读者快速入门TypeScript，包括环境搭建、基本语法、类型系统、面向对象编程、模块化等方面的内容。...","permalink":"/post/青训营--Typescript快速入门","photos":[],"count_time":{"symbolsCount":"19k","symbolsTime":"17 mins."},"categories":[{"name":"前端","slug":"前端","count":48,"path":"api/categories/前端.json"}],"tags":[{"name":"字节跳动青训营","slug":"字节跳动青训营","count":21,"path":"api/tags/字节跳动青训营.json"}],"author":{"name":"会思想的苇草i","slug":"blog-author","avatar":"/img/avatar.jpg","link":"/","description":"日拱一卒，功不唐捐 <br/> With each day's arduous effort,<br/>no achievement shall be in vain","socials":{"github":"https://github.com/Thinkingreedi","twitter":"","stackoverflow":"","wechat":"","qq":"","weibo":"","zhihu":"","csdn":"https://blog.csdn.net/ASHIYI66","juejin":"https://juejin.cn/user/4284166567110935","customs":{}}},"feature":false},{"title":"Web多媒体入门","uid":"cbeef85e3ef827f236c8157203105c9a","slug":"青训营--Web多媒体入门","date":"2022-02-05T10:40:59.000Z","updated":"2025-07-14T15:12:20.471Z","comments":true,"path":"api/articles/青训营--Web多媒体入门.json","keywords":"web前端开发,web前端博客,个人博客,html,css,javascript,vue,react","cover":"https://img-blog.csdnimg.cn/3112c385d3c845d4b0305beebbc3ffdf.jpeg","text":"Web多媒体是Web开发中的重要组成部分，它包括图像、音频和视频等多种形式。本文将介绍常见的Web图像格式（如JPEG、PNG、GIF等）及其特点、优缺点，并深入讨论如何使用CSS和JavaScript来实现Web图像的动态效果。...","permalink":"/post/青训营--Web多媒体入门","photos":[],"count_time":{"symbolsCount":"2.5k","symbolsTime":"2 mins."},"categories":[{"name":"前端","slug":"前端","count":48,"path":"api/categories/前端.json"}],"tags":[{"name":"字节跳动青训营","slug":"字节跳动青训营","count":21,"path":"api/tags/字节跳动青训营.json"}],"author":{"name":"会思想的苇草i","slug":"blog-author","avatar":"/img/avatar.jpg","link":"/","description":"日拱一卒，功不唐捐 <br/> With each day's arduous effort,<br/>no achievement shall be in vain","socials":{"github":"https://github.com/Thinkingreedi","twitter":"","stackoverflow":"","wechat":"","qq":"","weibo":"","zhihu":"","csdn":"https://blog.csdn.net/ASHIYI66","juejin":"https://juejin.cn/user/4284166567110935","customs":{}}},"feature":false},{"title":"数据结构基础","uid":"a4ba43b16c40c17ef43c675dbe1ccabe","slug":"数据结构（C语言版）-- 数据结构基础","date":"2022-01-31T02:10:54.000Z","updated":"2025-07-14T15:12:20.469Z","comments":true,"path":"api/articles/数据结构（C语言版）-- 数据结构基础.json","keywords":"web前端开发,web前端博客,个人博客,html,css,javascript,vue,react","cover":"https://img-blog.csdnimg.cn/a7ee138129bc4e54ae59143d2f81518d.png","text":"数据结构是计算机科学中的重要基础，它提供了存储和组织数据的方法。本文将引导读者了解并掌握数据结构的基本概念和原理。我们还将学习数据结构的算法操作，如查找、排序、插入、删除等，并讨论它们的时间复杂度和空间复杂度。...","permalink":"/post/数据结构（C语言版）-- 数据结构基础","photos":[],"count_time":{"symbolsCount":"1.4k","symbolsTime":"1 mins."},"categories":[{"name":"前端","slug":"前端","count":48,"path":"api/categories/前端.json"}],"tags":[{"name":"字节跳动青训营","slug":"字节跳动青训营","count":21,"path":"api/tags/字节跳动青训营.json"}],"author":{"name":"会思想的苇草i","slug":"blog-author","avatar":"/img/avatar.jpg","link":"/","description":"日拱一卒，功不唐捐 <br/> With each day's arduous effort,<br/>no achievement shall be in vain","socials":{"github":"https://github.com/Thinkingreedi","twitter":"","stackoverflow":"","wechat":"","qq":"","weibo":"","zhihu":"","csdn":"https://blog.csdn.net/ASHIYI66","juejin":"https://juejin.cn/user/4284166567110935","customs":{}}},"feature":true},{"title":"数据可视化基础","uid":"296a334cba71a48abd93af36204eaa13","slug":"青训营--数据可视化基础","date":"2022-01-30T06:57:04.000Z","updated":"2025-07-14T15:12:20.472Z","comments":true,"path":"api/articles/青训营--数据可视化基础.json","keywords":"web前端开发,web前端博客,个人博客,html,css,javascript,vue,react","cover":"https://img-blog.csdnimg.cn/3112c385d3c845d4b0305beebbc3ffdf.jpeg","text":"数据可视化基础是数据科学和分析领域中至关重要的一部分，它涉及将数据转换为图形化展示，以便更好地理解和推断数据。通过本文的学习，读者将能够掌握数据可视化的基本原理和技巧，为进一步深入学习和实践打下坚实的基础。...","permalink":"/post/青训营--数据可视化基础","photos":[],"count_time":{"symbolsCount":"2k","symbolsTime":"2 mins."},"categories":[{"name":"前端","slug":"前端","count":48,"path":"api/categories/前端.json"}],"tags":[{"name":"字节跳动青训营","slug":"字节跳动青训营","count":21,"path":"api/tags/字节跳动青训营.json"}],"author":{"name":"会思想的苇草i","slug":"blog-author","avatar":"/img/avatar.jpg","link":"/","description":"日拱一卒，功不唐捐 <br/> With each day's arduous effort,<br/>no achievement shall be in vain","socials":{"github":"https://github.com/Thinkingreedi","twitter":"","stackoverflow":"","wechat":"","qq":"","weibo":"","zhihu":"","csdn":"https://blog.csdn.net/ASHIYI66","juejin":"https://juejin.cn/user/4284166567110935","customs":{}}},"feature":false},{"title":"WEB开发的安全之旅","uid":"3de72e581df02b5836f80f8bb40e188c","slug":"青训营--WEB开发的安全之旅","date":"2022-01-28T03:01:14.000Z","updated":"2025-07-14T15:12:20.471Z","comments":true,"path":"api/articles/青训营--WEB开发的安全之旅.json","keywords":"web前端开发,web前端博客,个人博客,html,css,javascript,vue,react","cover":"https://img-blog.csdnimg.cn/3112c385d3c845d4b0305beebbc3ffdf.jpeg","text":"WEB开发的安全之旅是一段关于如何保护Web应用程序免受各种安全威胁的旅程。本文将引导读者了解并掌握WEB开发中的常见安全问题和对策。...","permalink":"/post/青训营--WEB开发的安全之旅","photos":[],"count_time":{"symbolsCount":"1.7k","symbolsTime":"2 mins."},"categories":[{"name":"前端","slug":"前端","count":48,"path":"api/categories/前端.json"}],"tags":[{"name":"字节跳动青训营","slug":"字节跳动青训营","count":21,"path":"api/tags/字节跳动青训营.json"}],"author":{"name":"会思想的苇草i","slug":"blog-author","avatar":"/img/avatar.jpg","link":"/","description":"日拱一卒，功不唐捐 <br/> With each day's arduous effort,<br/>no achievement shall be in vain","socials":{"github":"https://github.com/Thinkingreedi","twitter":"","stackoverflow":"","wechat":"","qq":"","weibo":"","zhihu":"","csdn":"https://blog.csdn.net/ASHIYI66","juejin":"https://juejin.cn/user/4284166567110935","customs":{}}},"feature":false},{"title":"Webpack知识体系","uid":"ce5090caf1cc811b128b2cdaa9bcbdd2","slug":"青训营--Webpack知识体系","date":"2022-01-27T14:36:23.000Z","updated":"2025-07-14T15:12:20.471Z","comments":true,"path":"api/articles/青训营--Webpack知识体系.json","keywords":"web前端开发,web前端博客,个人博客,html,css,javascript,vue,react","cover":"https://img-blog.csdnimg.cn/3112c385d3c845d4b0305beebbc3ffdf.jpeg","text":"Webpack是一款现代化的前端构建工具，被广泛用于打包、优化和管理JavaScript模块。本文将介绍Webpack的知识体系，帮助读者全面了解其核心概念和使用方法。...","permalink":"/post/青训营--Webpack知识体系","photos":[],"count_time":{"symbolsCount":"1.7k","symbolsTime":"2 mins."},"categories":[{"name":"前端","slug":"前端","count":48,"path":"api/categories/前端.json"}],"tags":[{"name":"字节跳动青训营","slug":"字节跳动青训营","count":21,"path":"api/tags/字节跳动青训营.json"}],"author":{"name":"会思想的苇草i","slug":"blog-author","avatar":"/img/avatar.jpg","link":"/","description":"日拱一卒，功不唐捐 <br/> With each day's arduous effort,<br/>no achievement shall be in vain","socials":{"github":"https://github.com/Thinkingreedi","twitter":"","stackoverflow":"","wechat":"","qq":"","weibo":"","zhihu":"","csdn":"https://blog.csdn.net/ASHIYI66","juejin":"https://juejin.cn/user/4284166567110935","customs":{}}},"feature":false},{"title":"WebGL初识","uid":"c2bb75f6dd30000ed3be30fb34a8fb6a","slug":"青训营--WebGL初识","date":"2022-01-26T01:59:26.000Z","updated":"2025-07-14T15:12:20.471Z","comments":true,"path":"api/articles/青训营--WebGL初识.json","keywords":"web前端开发,web前端博客,个人博客,html,css,javascript,vue,react","cover":"https://img-blog.csdnimg.cn/3112c385d3c845d4b0305beebbc3ffdf.jpeg","text":"WebGL是一种用于在Web浏览器中实现高性能3D图形的技术。本文将帮助读者快速入门WebGL，了解其基本概念和使用方法。我们将介绍WebGL的基本架构和API，包括如何创建WebGL上下文、渲染对象和着色器编程等。...","permalink":"/post/青训营--WebGL初识","photos":[],"count_time":{"symbolsCount":"1.2k","symbolsTime":"1 mins."},"categories":[{"name":"前端","slug":"前端","count":48,"path":"api/categories/前端.json"}],"tags":[{"name":"字节跳动青训营","slug":"字节跳动青训营","count":21,"path":"api/tags/字节跳动青训营.json"}],"author":{"name":"会思想的苇草i","slug":"blog-author","avatar":"/img/avatar.jpg","link":"/","description":"日拱一卒，功不唐捐 <br/> With each day's arduous effort,<br/>no achievement shall be in vain","socials":{"github":"https://github.com/Thinkingreedi","twitter":"","stackoverflow":"","wechat":"","qq":"","weibo":"","zhihu":"","csdn":"https://blog.csdn.net/ASHIYI66","juejin":"https://juejin.cn/user/4284166567110935","customs":{}}},"feature":false},{"title":"Node.js与前端开发实战","uid":"0182665cc415e72321b4209011c914e6","slug":"青训营--Node.js与前端开发实战","date":"2022-01-25T03:09:55.000Z","updated":"2025-07-14T15:12:20.471Z","comments":true,"path":"api/articles/青训营--Node.js与前端开发实战.json","keywords":"web前端开发,web前端博客,个人博客,html,css,javascript,vue,react","cover":"https://img-blog.csdnimg.cn/3112c385d3c845d4b0305beebbc3ffdf.jpeg","text":"在本文中，我们将探讨如何将Node.js与前端开发实战相结合。我们还会深入研究前端开发中常用的构建工具、自动化流程和部署技巧，以及如何通过Node.js优化前端开发工作流程。...","permalink":"/post/青训营--Node.js与前端开发实战","photos":[],"count_time":{"symbolsCount":"1.4k","symbolsTime":"1 mins."},"categories":[{"name":"前端","slug":"前端","count":48,"path":"api/categories/前端.json"}],"tags":[{"name":"字节跳动青训营","slug":"字节跳动青训营","count":21,"path":"api/tags/字节跳动青训营.json"}],"author":{"name":"会思想的苇草i","slug":"blog-author","avatar":"/img/avatar.jpg","link":"/","description":"日拱一卒，功不唐捐 <br/> With each day's arduous effort,<br/>no achievement shall be in vain","socials":{"github":"https://github.com/Thinkingreedi","twitter":"","stackoverflow":"","wechat":"","qq":"","weibo":"","zhihu":"","csdn":"https://blog.csdn.net/ASHIYI66","juejin":"https://juejin.cn/user/4284166567110935","customs":{}}},"feature":false},{"title":"Http实用指南","uid":"79d011c4f922321d4bb1c1cdb5390980","slug":"青训营--HTTP实用指南","date":"2022-01-24T02:38:04.000Z","updated":"2025-07-14T15:12:20.471Z","comments":true,"path":"api/articles/青训营--HTTP实用指南.json","keywords":"web前端开发,web前端博客,个人博客,html,css,javascript,vue,react","cover":"https://img-blog.csdnimg.cn/3112c385d3c845d4b0305beebbc3ffdf.jpeg","text":"HTTP实用指南是帮助开发人员理解和应用HTTP协议的重要资源。本文将介绍HTTP的基本概念，包括请求和响应的结构、状态码、请求方法等。...","permalink":"/post/青训营--HTTP实用指南","photos":[],"count_time":{"symbolsCount":"1.8k","symbolsTime":"2 mins."},"categories":[{"name":"前端","slug":"前端","count":48,"path":"api/categories/前端.json"}],"tags":[{"name":"字节跳动青训营","slug":"字节跳动青训营","count":21,"path":"api/tags/字节跳动青训营.json"}],"author":{"name":"会思想的苇草i","slug":"blog-author","avatar":"/img/avatar.jpg","link":"/","description":"日拱一卒，功不唐捐 <br/> With each day's arduous effort,<br/>no achievement shall be in vain","socials":{"github":"https://github.com/Thinkingreedi","twitter":"","stackoverflow":"","wechat":"","qq":"","weibo":"","zhihu":"","csdn":"https://blog.csdn.net/ASHIYI66","juejin":"https://juejin.cn/user/4284166567110935","customs":{}}},"feature":false},{"title":"前端动画实现","uid":"96f2401ef260a2fda3074e7c72b8a623","slug":"青训营--前端动画实现","date":"2022-01-21T08:11:16.000Z","updated":"2025-07-14T15:12:20.471Z","comments":true,"path":"api/articles/青训营--前端动画实现.json","keywords":"web前端开发,web前端博客,个人博客,html,css,javascript,vue,react","cover":"https://img-blog.csdnimg.cn/3112c385d3c845d4b0305beebbc3ffdf.jpeg","text":"在前端开发中，动画效果能够增强用户体验并提升页面吸引力。本文将介绍前端动画实现的多种方式，包括CSS动画、JavaScript动画库以及最新的Web动画API。通过学习本文，读者将掌握多种前端动画实现技术，从而丰富其网页设计与开发的技能。...","permalink":"/post/青训营--前端动画实现","photos":[],"count_time":{"symbolsCount":"3.4k","symbolsTime":"3 mins."},"categories":[{"name":"前端","slug":"前端","count":48,"path":"api/categories/前端.json"}],"tags":[{"name":"字节跳动青训营","slug":"字节跳动青训营","count":21,"path":"api/tags/字节跳动青训营.json"}],"author":{"name":"会思想的苇草i","slug":"blog-author","avatar":"/img/avatar.jpg","link":"/","description":"日拱一卒，功不唐捐 <br/> With each day's arduous effort,<br/>no achievement shall be in vain","socials":{"github":"https://github.com/Thinkingreedi","twitter":"","stackoverflow":"","wechat":"","qq":"","weibo":"","zhihu":"","csdn":"https://blog.csdn.net/ASHIYI66","juejin":"https://juejin.cn/user/4284166567110935","customs":{}}},"feature":false},{"title":"响应式系统与React","uid":"daa70c85e66020d3179c9d18aed40c23","slug":"青训营--响应式系统与React","date":"2022-01-21T07:55:49.000Z","updated":"2025-07-14T15:12:20.472Z","comments":true,"path":"api/articles/青训营--响应式系统与React.json","keywords":"web前端开发,web前端博客,个人博客,html,css,javascript,vue,react","cover":"https://img-blog.csdnimg.cn/3112c385d3c845d4b0305beebbc3ffdf.jpeg","text":"React是一个流行的JavaScript库，而响应式系统是现代前端开发中的重要概念。本文将探讨React与响应式系统之间的关系，包括React中的状态管理、组件的渲染机制以及响应式数据流的实现原理。...","permalink":"/post/青训营--响应式系统与React","photos":[],"count_time":{"symbolsCount":"2.3k","symbolsTime":"2 mins."},"categories":[{"name":"前端","slug":"前端","count":48,"path":"api/categories/前端.json"}],"tags":[{"name":"字节跳动青训营","slug":"字节跳动青训营","count":21,"path":"api/tags/字节跳动青训营.json"}],"author":{"name":"会思想的苇草i","slug":"blog-author","avatar":"/img/avatar.jpg","link":"/","description":"日拱一卒，功不唐捐 <br/> With each day's arduous effort,<br/>no achievement shall be in vain","socials":{"github":"https://github.com/Thinkingreedi","twitter":"","stackoverflow":"","wechat":"","qq":"","weibo":"","zhihu":"","csdn":"https://blog.csdn.net/ASHIYI66","juejin":"https://juejin.cn/user/4284166567110935","customs":{}}},"feature":false}]}